amber/__init__.py
amber/comparator.py
amber/metrics.py
amber/model.py
amber/utils.py
amber_embeddings-0.1.0.dist-info/licenses/LICENSE
amber_embeddings-0.1.0.dist-info/METADATA
amber_embeddings-0.1.0.dist-info/WHEEL
amber_embeddings-0.1.0.dist-info/top_level.txt
amber_embeddings-0.1.0.dist-info/RECORD
