Metadata-Version: 2.4
Name: amber-embeddings
Version: 0.1.0
Summary: Attention-based Multi-head Bidirectional Enhanced Representations for contextual word embeddings
Home-page: https://github.com/Saiyam-Sandhir-Jain/AMBER
Author: Saiyam Jain
Author-email: saiyam.sandhir.jain@gmail.com
Maintainer: Saiyam Jain
Maintainer-email: saiyam.sandhir.jain@gmail.com
Project-URL: Bug Tracker, https://github.com/Saiyam-Sandhir-Jain/AMBER/issues
Project-URL: Documentation, https://amber-embeddings.readthedocs.io/
Project-URL: Source Code, https://github.com/Saiyam-Sandhir-Jain/AMBER
Project-URL: Homepage, https://github.com/Saiyam-Sandhir-Jain/AMBER
Keywords: nlp,word-embeddings,attention,context-aware,word-sense-disambiguation,semantic-search,tfidf,word2vec,machine-learning,natural-language-processing
Classifier: Development Status :: 4 - Beta
Classifier: Intended Audience :: Developers
Classifier: Intended Audience :: Science/Research
Classifier: License :: OSI Approved :: MIT License
Classifier: Operating System :: OS Independent
Classifier: Programming Language :: Python :: 3
Classifier: Programming Language :: Python :: 3.7
Classifier: Programming Language :: Python :: 3.8
Classifier: Programming Language :: Python :: 3.9
Classifier: Programming Language :: Python :: 3.10
Classifier: Programming Language :: Python :: 3.11
Classifier: Topic :: Scientific/Engineering :: Artificial Intelligence
Classifier: Topic :: Text Processing :: Linguistic
Classifier: Topic :: Software Development :: Libraries :: Python Modules
Requires-Python: >=3.7
License-File: LICENSE
Requires-Dist: numpy>=1.19.0
Requires-Dist: scipy>=1.5.0
Requires-Dist: scikit-learn>=0.24.0
Requires-Dist: gensim>=4.0.0
Requires-Dist: pandas>=1.2.0
Requires-Dist: matplotlib>=3.3.0
Requires-Dist: seaborn>=0.11.0
Provides-Extra: dev
Requires-Dist: pytest>=6.0.0; extra == "dev"
Requires-Dist: pytest-cov>=2.10.0; extra == "dev"
Requires-Dist: black>=21.0.0; extra == "dev"
Requires-Dist: flake8>=3.8.0; extra == "dev"
Requires-Dist: isort>=5.0.0; extra == "dev"
Requires-Dist: mypy>=0.800; extra == "dev"
Provides-Extra: docs
Requires-Dist: sphinx>=4.0.0; extra == "docs"
Requires-Dist: sphinx-rtd-theme>=0.5.0; extra == "docs"
Requires-Dist: sphinx-autodoc-typehints>=1.12.0; extra == "docs"
Provides-Extra: test
Requires-Dist: pytest>=6.0.0; extra == "test"
Requires-Dist: pytest-cov>=2.10.0; extra == "test"
Requires-Dist: pytest-mock>=3.6.0; extra == "test"
Dynamic: author
Dynamic: author-email
Dynamic: classifier
Dynamic: description
Dynamic: description-content-type
Dynamic: home-page
Dynamic: keywords
Dynamic: license-file
Dynamic: maintainer
Dynamic: maintainer-email
Dynamic: project-url
Dynamic: provides-extra
Dynamic: requires-dist
Dynamic: requires-python
Dynamic: summary
